pyroid-0.7.0.dist-info/METADATA
pyroid-0.7.0.dist-info/WHEEL
pyroid/__init__.py
pyroid/async_bridge.py
pyroid/async_helpers.py
pyroid/async_impl.py
pyroid/async_ops.py
pyroid/core.py
pyroid/core/__init__.py
pyroid/core/buffer.py
pyroid/core/parallel.py
pyroid/core/runtime.py
pyroid/core_impl.py
pyroid/data.py
pyroid/data/__init__.py
pyroid/data_impl.py
pyroid/image.py
pyroid/image/__init__.py
pyroid/image/basic/__init__.py
pyroid/image_impl.py
pyroid/io.py
pyroid/io/__init__.py
pyroid/io_impl.py
pyroid/math.py
pyroid/math/__init__.py
pyroid/math/stats.py
pyroid/math_impl.py
pyroid/ml.py
pyroid/ml/__init__.py
pyroid/ml/basic/__init__.py
pyroid/ml_impl.py
pyroid/pyroid.abi3.so
pyroid/string/__init__.py
pyroid/text.py
pyroid/text/__init__.py
pyroid/text_impl.py
pyroid-0.7.0.dist-info/RECORD
