Metadata-Version: 2.4
Name: pyroid
Version: 0.7.0
Classifier: Programming Language :: Python :: 3
Classifier: Programming Language :: Python :: 3.8
Classifier: Programming Language :: Python :: 3.9
Classifier: Programming Language :: Python :: 3.10
Classifier: Programming Language :: Python :: 3.11
Classifier: Programming Language :: Rust
Classifier: License :: OSI Approved :: MIT License
Classifier: Operating System :: OS Independent
Classifier: Development Status :: 3 - Alpha
Classifier: Intended Audience :: Developers
Classifier: Topic :: Software Development :: Libraries :: Python Modules
Summary: High-performance Rust functions for Python with a simplified architecture
Author: Andrew O, Pyroid Team
Author-email: Pyroid Team <support@ataiva.com>
License: MIT
Requires-Python: >=3.8
Project-URL: Homepage, https://github.com/ao/pyroid
Project-URL: Bug Tracker, https://github.com/ao/pyroid/issues
Project-URL: Documentation, https://github.com/ao/pyroid/blob/main/README.md
